niftyfetcher/__init__.py
niftyfetcher/main.py
niftyfetcher-0.1.3.dist-info/METADATA
niftyfetcher-0.1.3.dist-info/WHEEL
niftyfetcher-0.1.3.dist-info/entry_points.txt
niftyfetcher-0.1.3.dist-info/licenses/LICENSE
niftyfetcher-0.1.3.dist-info/RECORD
