Metadata-Version: 2.4
Name: niftyfetcher
Version: 0.1.3
Summary: 📈 A CLI tool to fetch historical OHLC data for stocks using Upstox API
Project-URL: Homepage, https://github.com/yash2002vardhan/niftyfetcher
Project-URL: Repository, https://github.com/yash2002vardhan/niftyfetcher
Project-URL: Issues, https://github.com/yash2002vardhan/niftyfetcher/issues
Author-email: Yashvardhan Goel <yash2002@gmail.com>
License: MIT
License-File: LICENSE
Keywords: cli,data,historical,market,nifty,stock,trading,upstox
Classifier: Development Status :: 4 - Beta
Classifier: License :: OSI Approved :: MIT License
Classifier: Operating System :: OS Independent
Classifier: Programming Language :: Python :: 3
Classifier: Topic :: Office/Business :: Financial
Requires-Python: >=3.8
Requires-Dist: pandas>=1.3.0
Requires-Dist: requests>=2.25.0
Requires-Dist: typer[all]>=0.9.0
